Metadata-Version: 2.1
Name: turing-machine-executor
Version: 1.1.1
Summary: A Turing Machine executor
Home-page: https://github.com/espositoandrea/Turing-Machine-Executor
Author: Andrea Esposito
Author-email: esposito_andrea99@hotmail.com
License: MIT
Download-URL: https://github.com/espositoandrea/Turing-Machine-Executor/archive/v1.1.0-alpha.tar.gz
Keywords: Turing,Machine,Executor,EMT
Platform: UNKNOWN
Classifier: Development Status :: 3 - Alpha
Classifier: Intended Audience :: Education
Classifier: Topic :: Education
Classifier: License :: OSI Approved :: MIT License
Classifier: Programming Language :: Python :: 3
Classifier: Programming Language :: Python :: 3.4
Classifier: Programming Language :: Python :: 3.5
Classifier: Programming Language :: Python :: 3.6
